odoo/addons/server_environment_delivery/README.rst
odoo/addons/server_environment_delivery/__init__.py
odoo/addons/server_environment_delivery/__manifest__.py
odoo/addons/server_environment_delivery/i18n/server_environment_delivery.pot
odoo/addons/server_environment_delivery/models/__init__.py
odoo/addons/server_environment_delivery/models/delivery_carrier.py
odoo/addons/server_environment_delivery/readme/CONFIGURE.rst
odoo/addons/server_environment_delivery/readme/CONTRIBUTORS.rst
odoo/addons/server_environment_delivery/readme/DESCRIPTION.rst
odoo/addons/server_environment_delivery/static/description/icon.png
odoo/addons/server_environment_delivery/static/description/index.html
odoo13_addon_server_environment_delivery-13.0.1.0.1.dev3.dist-info/METADATA
odoo13_addon_server_environment_delivery-13.0.1.0.1.dev3.dist-info/WHEEL
odoo13_addon_server_environment_delivery-13.0.1.0.1.dev3.dist-info/top_level.txt
odoo13_addon_server_environment_delivery-13.0.1.0.1.dev3.dist-info/RECORD
